terminaloverflow/__init__.py
terminaloverflow/command_info_manager.py
terminaloverflow/command_parse_manager.py
terminaloverflow/history_command_manager.py
terminaloverflow/list_button.py
terminaloverflow/publish_subscribe_manager.py
terminaloverflow/settings_manager.py
terminaloverflow/social_search_manager.py
terminaloverflow/terminal_overflow_command_info_module.py
terminaloverflow/terminal_overflow_loader.py
terminaloverflow/terminal_overflow_search_module.py
terminaloverflow/terminal_overflow_settings_module.py
terminaloverflow-1.0.0.dist-info/LICENSE.txt
terminaloverflow-1.0.0.dist-info/METADATA
terminaloverflow-1.0.0.dist-info/RECORD
terminaloverflow-1.0.0.dist-info/WHEEL
terminaloverflow-1.0.0.dist-info/entry_points.txt
terminaloverflow-1.0.0.dist-info/top_level.txt
