Metadata-Version: 2.1
Name: terminaloverflow
Version: 1.0.0
Summary: Visual terminal experience with mouse support
Home-page: https://github.com/dazcode/terminaloverflow
Author: dazcode
Author-email: dazcode@gmail.com
License: UNKNOWN
Project-URL: Funding, https://github.com/dazcode/terminaloverflow
Project-URL: Bug Reports, https://github.com/dazcode/terminaloverflow
Project-URL: Say Thanks!, https://github.com/dazcode/terminaloverflow
Project-URL: Source, https://github.com/dazcode/terminaloverflow/
Keywords: terminal overflow
Platform: UNKNOWN
Classifier: Development Status :: 3 - Alpha
Classifier: Intended Audience :: Developers
Classifier: Topic :: System :: Shells
Classifier: License :: OSI Approved :: MIT License
Classifier: Programming Language :: Python :: 2.7
Requires-Dist: urwid
Requires-Dist: simplejson
